{
  "unicode": "1F47E",
  "slug": "alien-monster",
  "character": "👾",
  "name": "Alien Monster",
  "shortName": "alien-monster",
  "category": "smileys",
  "subcategory": "face-costume",
  "unicodeVersion": "6.0",
  "baseMeaning": "A purple, pixelated alien character from classic arcade games like Space Invaders.",
  "tldr": "Video games, retro gaming, or nerdy interests.",
  "contextMeanings": [
    {
      "context": "LITERAL",
      "meaning": "Referencing video games or gaming culture.",
      "example": "Gaming night! 👾",
      "riskLevel": "LOW"
    },
    {
      "context": "SLANG",
      "meaning": "Indicates geeky or nerdy interests.",
      "example": "Finally beat that boss 👾",
      "riskLevel": "LOW"
    },
    {
      "context": "DATING",
      "meaning": "Bonding over shared gaming interests.",
      "example": "You play retro games too? 👾",
      "riskLevel": "LOW"
    },
    {
      "context": "IRONIC",
      "meaning": "Used for nostalgic or 'old school' references.",
      "example": "Kids today will never know 👾",
      "riskLevel": "LOW"
    }
  ],
  "platformNotes": [
    { "platform": "TWITTER", "note": "Popular in gaming community and tech circles." },
    { "platform": "INSTAGRAM", "note": "Used in retro aesthetic and gaming posts." },
    { "platform": "TIKTOK", "note": "Common in gaming and nostalgia content." }
  ],
  "generationalNotes": [
    { "generation": "GEN_Z", "note": "Associated with gaming and retro aesthetics." },
    { "generation": "MILLENNIAL", "note": "Nostalgic connection to childhood arcade games." },
    { "generation": "BOOMER", "note": "May recognize from original Space Invaders." }
  ],
  "warnings": [],
  "relatedCombos": [],
  "seoTitle": "👾 Alien Monster Emoji Meaning - What Does 👾 Really Mean?",
  "seoDescription": "Learn what the alien monster emoji 👾 really means. From gaming culture to retro vibes, discover all the uses of this Space Invaders emoji."
}
