{
  "unicode": "U+1FAB2",
  "slug": "beetle-emoji",
  "character": "🪲",
  "name": "Beetle",
  "shortName": "beetle emoji",
  "category": "Animals & Nature",
  "subcategory": "Animal Bug",
  "unicodeVersion": "13.0",
  "baseMeaning": "Black beetle",
  "tldr": "Bug",
  "contextMeanings": [
    {
      "context": "LITERAL",
      "meaning": "Beetle",
      "example": "Black 🪲",
      "riskLevel": "LOW"
    },
    {
      "context": "SLANG",
      "meaning": "VW Beetle car",
      "example": "Love the 🪲",
      "riskLevel": "LOW"
    }
  ],
  "platformNotes": [
    {
      "platform": "TWITTER",
      "note": "Renders consistently across the platform"
    },
    {
      "platform": "INSTAGRAM",
      "note": "Common in stories and posts"
    }
  ],
  "generationalNotes": [
    {
      "generation": "GEN_Z",
      "note": "Used in various creative contexts"
    },
    {
      "generation": "MILLENNIAL",
      "note": "Straightforward usage"
    }
  ],
  "warnings": [],
  "relatedCombos": [],
  "seoTitle": "🪲 Beetle Emoji Meaning - What Does 🪲 Really Mean?",
  "seoDescription": "Learn what the beetle emoji 🪲 really means in texts and social media."
}
