{
  "unicode": "1F5A4",
  "slug": "black-heart",
  "character": "🖤",
  "name": "Black Heart",
  "shortName": "black heart",
  "category": "symbols",
  "subcategory": "emotion",
  "unicodeVersion": "9.0",
  "baseMeaning": "Black Heart emoji.",
  "tldr": "Dark or edgy! Grief, goth aesthetic, or dark humor.",
  "contextMeanings": [
    {
      "context": "LITERAL",
      "meaning": "Represents grief, sorrow, or dark emotions.",
      "example": "RIP 🖤",
      "riskLevel": "LOW"
    },
    {
      "context": "SLANG",
      "meaning": "Goth or edgy aesthetic.",
      "example": "My soul 🖤",
      "riskLevel": "LOW"
    },
    {
      "context": "IRONIC",
      "meaning": "Dark humor or sarcasm.",
      "example": "Love Mondays 🖤",
      "riskLevel": "LOW"
    },
    {
      "context": "DATING",
      "meaning": "Deep, intense love or dark romance.",
      "example": "You're my darkness 🖤",
      "riskLevel": "LOW"
    }
  ],
  "platformNotes": [
    { "platform": "TWITTER", "note": "Common in alt communities." },
    { "platform": "INSTAGRAM", "note": "Popular for dark aesthetics." },
    { "platform": "TIKTOK", "note": "Goth and emo content." }
  ],
  "generationalNotes": [
    { "generation": "GEN_Z", "note": "Edgy and aesthetic." },
    { "generation": "MILLENNIAL", "note": "Emo nostalgia." },
    { "generation": "BOOMER", "note": "May interpret as sad or morbid." }
  ],
  "warnings": [],
  "relatedCombos": [],
  "seoTitle": "🖤 Black Heart Emoji Meaning",
  "seoDescription": "Learn what the Black Heart emoji 🖤 really means."
}
