{
  "unicode": "1F7E4",
  "slug": "brown-circle-emoji",
  "character": "🟤",
  "name": "Brown Circle",
  "shortName": "brown circle emoji",
  "category": "symbols",
  "subcategory": "geometric",
  "unicodeVersion": "13.0",
  "baseMeaning": "A brown circle.",
  "tldr": "Represents brown.",
  "contextMeanings": [
    {
      "context": "LITERAL",
      "meaning": "A brown dot.",
      "example": "Brown circle 🟤",
      "riskLevel": "LOW"
    },
    {
      "context": "SLANG",
      "meaning": "Earthy.",
      "example": "Natural 🟤",
      "riskLevel": "LOW"
    }
  ],
  "platformNotes": [
    {
      "platform": "TWITTER",
      "note": "Used in posts about brown circle."
    },
    {
      "platform": "INSTAGRAM",
      "note": "Popular in captions and stories."
    },
    {
      "platform": "TIKTOK",
      "note": "Common in comments and reactions."
    }
  ],
  "generationalNotes": [
    {
      "generation": "GEN_Z",
      "note": "Uses 🟤 in casual contexts."
    },
    {
      "generation": "MILLENNIAL",
      "note": "Familiar with 🟤 across platforms."
    },
    {
      "generation": "BOOMER",
      "note": "May use 🟤 literally."
    }
  ],
  "warnings": [],
  "relatedCombos": [],
  "seoTitle": "🟤 Brown Circle Emoji Meaning - What Does 🟤 Really Mean?",
  "seoDescription": "Learn what the brown circle emoji 🟤 really means in texts and social media."
}
