{
  "unicode": "274C",
  "slug": "cross-mark",
  "character": "❌",
  "name": "Cross Mark",
  "shortName": "x",
  "category": "symbols",
  "subcategory": "other-symbol",
  "unicodeVersion": "6.0",
  "baseMeaning": "Cross mark indicating rejection.",
  "tldr": "No! Wrong or rejected.",
  "contextMeanings": [
    {
      "context": "LITERAL",
      "meaning": "Represents rejection or something wrong.",
      "example": "Wrong answer ❌",
      "riskLevel": "LOW"
    },
    {
      "context": "SLANG",
      "meaning": "Strong disagreement or cancellation.",
      "example": "That's a no ❌",
      "riskLevel": "LOW"
    },
    {
      "context": "PASSIVE_AGGRESSIVE",
      "meaning": "Dismissing someone or something.",
      "example": "Your opinion ❌",
      "riskLevel": "MEDIUM"
    },
    {
      "context": "WORK",
      "meaning": "Incorrect or rejected.",
      "example": "Not approved ❌",
      "riskLevel": "LOW"
    }
  ],
  "platformNotes": [
    { "platform": "TWITTER", "note": "Strong rejection or disagreement." },
    { "platform": "INSTAGRAM", "note": "Comparison posts (do vs don't)." },
    { "platform": "SLACK", "note": "Task not done or rejected." }
  ],
  "generationalNotes": [
    { "generation": "GEN_Z", "note": "Cancel culture symbol." },
    { "generation": "MILLENNIAL", "note": "Strong no." },
    { "generation": "BOOMER", "note": "Incorrect mark." }
  ],
  "warnings": [],
  "relatedCombos": [],
  "seoTitle": "❌ Cross Mark Emoji Meaning",
  "seoDescription": "Learn what the Cross Mark emoji ❌ really means."
}
