{
  "unicode": "1F369",
  "slug": "donut",
  "character": "游꼴",
  "name": "Doughnut",
  "shortName": "donut",
  "category": "food",
  "subcategory": "food-sweet",
  "unicodeVersion": "6.0",
  "baseMeaning": "A doughnut with chocolate or pink frosting.",
  "tldr": "Donuts, treats, police stereotype, or Homer Simpson reference.",
  "contextMeanings": [
    {
      "context": "LITERAL",
      "meaning": "Donuts or sweet treats.",
      "example": "Donut run 游꼴",
      "riskLevel": "LOW"
    },
    {
      "context": "SLANG",
      "meaning": "Treating yourself or indulgence.",
      "example": "I deserve this donut 游꼴",
      "riskLevel": "LOW"
    },
    {
      "context": "WORK",
      "meaning": "Office treats or meetings.",
      "example": "Donuts in the break room 游꼴",
      "riskLevel": "LOW"
    },
    {
      "context": "IRONIC",
      "meaning": "Homer Simpson or cop stereotypes.",
      "example": "Mmm donuts 游꼴",
      "riskLevel": "LOW"
    }
  ],
  "platformNotes": [
    {
      "platform": "INSTAGRAM",
      "note": "Food content and treat posts."
    },
    {
      "platform": "TWITTER",
      "note": "Food discussions and Simpsons references."
    },
    {
      "platform": "SLACK",
      "note": "Office treat announcements."
    }
  ],
  "generationalNotes": [
    {
      "generation": "GEN_Z",
      "note": "Sweet treat and aesthetic."
    },
    {
      "generation": "MILLENNIAL",
      "note": "Homer Simpson and treat yo self."
    },
    {
      "generation": "BOOMER",
      "note": "Donuts and bakery."
    }
  ],
  "warnings": [],
  "relatedCombos": [],
  "seoTitle": "游꼴 Donut Emoji Meaning - What Does 游꼴 Really Mean?",
  "seoDescription": "Learn what the donut emoji 游꼴 really means in texting. Sweet treats or Homer Simpson vibes. Complete context guide."
}
