{
  "unicode": "U+1F1EA-1F1E8",
  "slug": "ecuador-flag-emoji",
  "character": "🇪🇨",
  "name": "Ecuador Flag",
  "shortName": "EC flag",
  "category": "Flags",
  "subcategory": "Country Flag",
  "unicodeVersion": "6.0",
  "baseMeaning": "Flag of Ecuador",
  "tldr": "Ecuador national flag",
  "contextMeanings": [
    {
      "context": "LITERAL",
      "meaning": "Represents Ecuador",
      "example": "From 🇪🇨",
      "riskLevel": "LOW"
    },
    {
      "context": "SLANG",
      "meaning": "Ecuador identity or culture",
      "example": "🇪🇨 pride",
      "riskLevel": "LOW"
    }
  ],
  "platformNotes": [
    {
      "platform": "TWITTER",
      "note": "Renders as country flag"
    },
    {
      "platform": "INSTAGRAM",
      "note": "Common in travel and location posts"
    }
  ],
  "generationalNotes": [
    {
      "generation": "GEN_Z",
      "note": "Used in travel and cultural contexts"
    },
    {
      "generation": "MILLENNIAL",
      "note": "Straightforward flag usage"
    }
  ],
  "warnings": [],
  "relatedCombos": [],
  "seoTitle": "🇪🇨 Ecuador Flag Emoji - What Does 🇪🇨 Mean?",
  "seoDescription": "Learn what the Ecuador flag emoji 🇪🇨 means in texts and social media."
}
