{
  "unicode": "1F50C",
  "slug": "electric-plug",
  "character": "🔌",
  "name": "Electric Plug",
  "shortName": "electric-plug",
  "category": "objects",
  "subcategory": "computer",
  "unicodeVersion": "6.0",
  "baseMeaning": "An electric plug.",
  "tldr": "Power, connection, or plug something.",
  "contextMeanings": [
    {
      "context": "LITERAL",
      "meaning": "Electric plug.",
      "example": "Plug in 🔌",
      "riskLevel": "LOW"
    },
    {
      "context": "SLANG",
      "meaning": "The plug (supplier).",
      "example": "Got the plug 🔌",
      "riskLevel": "MEDIUM"
    },
    {
      "context": "WORK",
      "meaning": "Connection.",
      "example": "Plugging in 🔌",
      "riskLevel": "LOW"
    },
    {
      "context": "IRONIC",
      "meaning": "Self promotion.",
      "example": "Shameless plug 🔌",
      "riskLevel": "LOW"
    }
  ],
  "platformNotes": [
    { "platform": "TWITTER", "note": "Promotions." },
    { "platform": "INSTAGRAM", "note": "Sponsorships." },
    { "platform": "TIKTOK", "note": "Product plugs." }
  ],
  "generationalNotes": [
    { "generation": "GEN_Z", "note": "The plug." },
    { "generation": "MILLENNIAL", "note": "Self promo." },
    { "generation": "BOOMER", "note": "Power connection." }
  ],
  "warnings": [],
  "relatedCombos": [],
  "seoTitle": "🔌 Electric Plug Emoji Meaning - What Does 🔌 Really Mean?",
  "seoDescription": "Learn what the electric plug emoji 🔌 really means. Power or plug vibes. Complete context guide."
}
