{
  "unicode": "1F979",
  "slug": "face-holding-back-tears",
  "character": "🥹",
  "name": "Face Holding Back Tears",
  "shortName": "touched",
  "category": "faces",
  "subcategory": "face-concerned",
  "unicodeVersion": "14.0",
  "baseMeaning": "A face with glossy eyes, holding back tears of emotion.",
  "tldr": "Touched, moved, about to happy-cry. The 'this is so wholesome' face.",
  "contextMeanings": [
    {
      "context": "SLANG",
      "meaning": "Touched or emotionally moved.",
      "example": "That video 🥹",
      "riskLevel": "LOW"
    },
    {
      "context": "LITERAL",
      "meaning": "About to cry from emotion.",
      "example": "I'm not crying 🥹",
      "riskLevel": "LOW"
    },
    {
      "context": "DATING",
      "meaning": "Moved by romantic gestures.",
      "example": "You remembered 🥹",
      "riskLevel": "LOW"
    },
    {
      "context": "IRONIC",
      "meaning": "Overly emotional about small things.",
      "example": "They said I did a good job 🥹",
      "riskLevel": "LOW"
    }
  ],
  "platformNotes": [
    { "platform": "TIKTOK", "note": "Wholesome content reactions." },
    { "platform": "TWITTER", "note": "Emotional and heartwarming posts." },
    { "platform": "INSTAGRAM", "note": "Sweet comments and moments." }
  ],
  "generationalNotes": [
    { "generation": "GEN_Z", "note": "Wholesome reactions and being touched." },
    { "generation": "MILLENNIAL", "note": "Emotionally moved." },
    { "generation": "BOOMER", "note": "Newer emoji, may not be familiar." }
  ],
  "warnings": [],
  "relatedCombos": [],
  "seoTitle": "🥹 Face Holding Back Tears Emoji Meaning - What Does 🥹 Really Mean?",
  "seoDescription": "Learn what the face holding back tears emoji 🥹 really means. Touched, moved, or wholesome. Complete context guide."
}
