{
  "unicode": "1F606",
  "slug": "grinning-squinting",
  "character": "😆",
  "name": "Grinning Squinting Face",
  "shortName": "laughing",
  "category": "smileys",
  "subcategory": "face-smiling",
  "unicodeVersion": "6.0",
  "baseMeaning": "A yellow face with a broad, open smile and scrunched, X-shaped eyes, laughing hard.",
  "tldr": "Laughing hard, extremely amused, or ecstatic.",
  "contextMeanings": [
    {
      "context": "LITERAL",
      "meaning": "Laughing very hard at something funny.",
      "example": "That joke killed me 😆",
      "riskLevel": "LOW"
    },
    {
      "context": "SLANG",
      "meaning": "Indicates finding something hilarious.",
      "example": "Did you see that fail video 😆",
      "riskLevel": "LOW"
    },
    {
      "context": "DATING",
      "meaning": "Shows you find them genuinely funny.",
      "example": "You always make me laugh 😆",
      "riskLevel": "LOW"
    },
    {
      "context": "IRONIC",
      "meaning": "Can express nervous laughter or laughing at misfortune.",
      "example": "My car broke down again 😆",
      "riskLevel": "LOW"
    }
  ],
  "platformNotes": [
    { "platform": "TWITTER", "note": "Common reaction to funny tweets and memes." },
    { "platform": "INSTAGRAM", "note": "Used in comments on comedy content." },
    { "platform": "TIKTOK", "note": "Popular reaction to funny videos." }
  ],
  "generationalNotes": [
    { "generation": "GEN_Z", "note": "Often replaced by skull emoji for extreme humor." },
    { "generation": "MILLENNIAL", "note": "Standard emoji for laughing hard." },
    { "generation": "BOOMER", "note": "Used to show something is very funny." }
  ],
  "warnings": [],
  "relatedCombos": [],
  "seoTitle": "😆 Grinning Squinting Face Emoji Meaning - What Does 😆 Really Mean?",
  "seoDescription": "Learn what the grinning squinting face emoji 😆 really means. This laughing emoji explained for texts, social media, and more."
}
