{
  "unicode": "1F3E5",
  "slug": "hospital",
  "character": "🏥",
  "name": "Hospital",
  "shortName": "hospital",
  "category": "travel-places",
  "subcategory": "place-building",
  "unicodeVersion": "6.0",
  "baseMeaning": "Hospital emoji.",
  "tldr": "Health! Hospital or medical.",
  "contextMeanings": [
    {
      "context": "LITERAL",
      "meaning": "Represents Hospital.",
      "example": "Check this out 🏥",
      "riskLevel": "LOW"
    },
    {
      "context": "SLANG",
      "meaning": "Common slang usage.",
      "example": "Vibes 🏥",
      "riskLevel": "LOW"
    },
    { "context": "IRONIC", "meaning": "Ironic usage.", "example": "Mood 🏥", "riskLevel": "LOW" },
    {
      "context": "WORK",
      "meaning": "Professional context.",
      "example": "Work stuff 🏥",
      "riskLevel": "LOW"
    }
  ],
  "platformNotes": [
    { "platform": "TWITTER", "note": "Common on Twitter." },
    { "platform": "INSTAGRAM", "note": "Popular on Instagram." },
    { "platform": "TIKTOK", "note": "Used on TikTok." }
  ],
  "generationalNotes": [
    { "generation": "GEN_Z", "note": "Gen Z usage." },
    { "generation": "MILLENNIAL", "note": "Millennial usage." },
    { "generation": "BOOMER", "note": "Boomer interpretation." }
  ],
  "warnings": [],
  "relatedCombos": [],
  "seoTitle": "🏥 Hospital Emoji Meaning",
  "seoDescription": "Learn what the Hospital emoji 🏥 really means."
}
