{
  "unicode": "1F336",
  "slug": "hot-pepper",
  "character": "🌶️",
  "name": "Hot Pepper",
  "shortName": "pepper",
  "category": "food",
  "subcategory": "food-vegetable",
  "unicodeVersion": "7.0",
  "baseMeaning": "A red hot pepper.",
  "tldr": "Spicy, hot takes, or attractive person.",
  "contextMeanings": [
    {
      "context": "LITERAL",
      "meaning": "Spicy food.",
      "example": "Extra spicy 🌶️",
      "riskLevel": "LOW"
    },
    {
      "context": "SLANG",
      "meaning": "Hot take or controversial.",
      "example": "Hot take 🌶️",
      "riskLevel": "LOW"
    },
    {
      "context": "DATING",
      "meaning": "Someone is hot.",
      "example": "Looking 🌶️",
      "riskLevel": "LOW"
    },
    {
      "context": "WORK",
      "meaning": "Spicy content.",
      "example": "Spicy update 🌶️",
      "riskLevel": "LOW"
    }
  ],
  "platformNotes": [
    { "platform": "TWITTER", "note": "Hot takes and spicy content." },
    { "platform": "INSTAGRAM", "note": "Food and attractive content." },
    { "platform": "TIKTOK", "note": "Spicy content." }
  ],
  "generationalNotes": [
    { "generation": "GEN_Z", "note": "Spicy takes." },
    { "generation": "MILLENNIAL", "note": "Hot takes." },
    { "generation": "BOOMER", "note": "Spicy food." }
  ],
  "warnings": [],
  "relatedCombos": [],
  "seoTitle": "🌶️ Hot Pepper Emoji Meaning - What Does 🌶️ Really Mean?",
  "seoDescription": "Learn what the hot pepper emoji 🌶️ really means. Spicy or hot vibes. Complete context guide."
}
