{
  "unicode": "1F368",
  "slug": "ice-cream",
  "character": "🍨",
  "name": "Ice Cream",
  "shortName": "ice-cream",
  "category": "food",
  "subcategory": "food-sweet",
  "unicodeVersion": "6.0",
  "baseMeaning": "A bowl or sundae of ice cream.",
  "tldr": "Ice cream, treating yourself, summer vibes, or comfort food.",
  "contextMeanings": [
    {
      "context": "LITERAL",
      "meaning": "Ice cream or frozen desserts.",
      "example": "Ice cream date! 🍨",
      "riskLevel": "LOW"
    },
    {
      "context": "SLANG",
      "meaning": "Treating yourself or comfort food.",
      "example": "Bad day calls for ice cream 🍨",
      "riskLevel": "LOW"
    },
    {
      "context": "DATING",
      "meaning": "Cute, casual date activity.",
      "example": "Let's get ice cream 🍨",
      "riskLevel": "LOW"
    },
    {
      "context": "IRONIC",
      "meaning": "Emotional eating or self-care.",
      "example": "Post-breakup vibes 🍨",
      "riskLevel": "LOW"
    }
  ],
  "platformNotes": [
    {
      "platform": "INSTAGRAM",
      "note": "Popular for dessert and summer content."
    },
    {
      "platform": "TIKTOK",
      "note": "Used in food reviews and summer videos."
    },
    {
      "platform": "TWITTER",
      "note": "Common in self-care and comfort food posts."
    }
  ],
  "generationalNotes": [
    {
      "generation": "GEN_Z",
      "note": "Comfort food and summer vibes."
    },
    {
      "generation": "MILLENNIAL",
      "note": "Self-care and nostalgia."
    },
    {
      "generation": "BOOMER",
      "note": "Straightforward ice cream reference."
    }
  ],
  "warnings": [],
  "relatedCombos": [],
  "seoTitle": "🍨 Ice Cream Emoji Meaning - What Does 🍨 Really Mean?",
  "seoDescription": "Learn what the ice cream emoji 🍨 really means in texting. Sweet treats, comfort food, or summer vibes. Complete context guide."
}
