{
  "unicode": "267E",
  "slug": "infinity",
  "character": "♾️",
  "name": "Infinity",
  "shortName": "infinity",
  "category": "symbols",
  "subcategory": "math",
  "unicodeVersion": "4.1",
  "baseMeaning": "The infinity symbol.",
  "tldr": "Forever, endless, or infinite possibilities.",
  "contextMeanings": [
    { "context": "LITERAL", "meaning": "Infinity.", "example": "Forever ♾️", "riskLevel": "LOW" },
    {
      "context": "SLANG",
      "meaning": "Endless love.",
      "example": "Love you ♾️",
      "riskLevel": "LOW"
    },
    {
      "context": "DATING",
      "meaning": "Forever together.",
      "example": "You and me ♾️",
      "riskLevel": "LOW"
    },
    {
      "context": "WORK",
      "meaning": "Infinite scroll.",
      "example": "Meetings ♾️",
      "riskLevel": "LOW"
    }
  ],
  "platformNotes": [
    { "platform": "INSTAGRAM", "note": "Relationship posts." },
    { "platform": "TWITTER", "note": "Forever vibes." },
    { "platform": "WHATSAPP", "note": "Love messages." }
  ],
  "generationalNotes": [
    { "generation": "GEN_Z", "note": "Infinite vibes." },
    { "generation": "MILLENNIAL", "note": "Forever and always." },
    { "generation": "BOOMER", "note": "Math symbol." }
  ],
  "warnings": [],
  "relatedCombos": [],
  "seoTitle": "♾️ Infinity Emoji Meaning - What Does ♾️ Really Mean?",
  "seoDescription": "Learn what the infinity emoji ♾️ really means. Forever or endless vibes. Complete context guide."
}
