{
  "unicode": "1F4A1",
  "slug": "light-bulb",
  "character": "💡",
  "name": "Light Bulb",
  "shortName": "lightbulb",
  "category": "objects",
  "subcategory": "light-video",
  "unicodeVersion": "6.0",
  "baseMeaning": "A light bulb, representing an idea or inspiration.",
  "tldr": "Idea! Used for having ideas, inspiration, or eureka moments.",
  "contextMeanings": [
    {
      "context": "LITERAL",
      "meaning": "Light or illumination.",
      "example": "Need new bulbs 💡",
      "riskLevel": "LOW"
    },
    {
      "context": "SLANG",
      "meaning": "Having an idea or realization.",
      "example": "Wait, I have an idea 💡",
      "riskLevel": "LOW"
    },
    {
      "context": "WORK",
      "meaning": "Innovation, creativity, or brainstorming.",
      "example": "💡 What if we tried...",
      "riskLevel": "LOW"
    },
    {
      "context": "IRONIC",
      "meaning": "Sarcastic 'genius' moment for obvious ideas.",
      "example": "Maybe we should just ask them 💡",
      "riskLevel": "LOW"
    }
  ],
  "platformNotes": [
    {
      "platform": "SLACK",
      "note": "Essential for brainstorming and idea sharing."
    },
    {
      "platform": "TWITTER",
      "note": "Used for sharing insights and ideas."
    },
    {
      "platform": "INSTAGRAM",
      "note": "Common in motivation and creativity content."
    }
  ],
  "generationalNotes": [
    {
      "generation": "GEN_Z",
      "note": "Ideas and eureka moments."
    },
    {
      "generation": "MILLENNIAL",
      "note": "Innovation and brainstorming."
    },
    {
      "generation": "BOOMER",
      "note": "Light bulb = idea (universal)."
    }
  ],
  "warnings": [],
  "relatedCombos": [],
  "seoTitle": "💡 Light Bulb Emoji Meaning - What Does 💡 Really Mean?",
  "seoDescription": "Learn what the light bulb emoji 💡 really means. Used for ideas, inspiration, and eureka moments. Complete context guide."
}
