{
  "unicode": "1F981",
  "slug": "lion-face",
  "character": "游부",
  "name": "Lion",
  "shortName": "lion face",
  "category": "animals",
  "subcategory": "animal-mammal",
  "unicodeVersion": "13.0",
  "baseMeaning": "Lion emoji.",
  "tldr": "Represents lion.",
  "contextMeanings": [
    {
      "context": "LITERAL",
      "meaning": "The lion animal.",
      "example": "Look, a lion! 游부",
      "riskLevel": "LOW"
    },
    {
      "context": "SLANG",
      "meaning": "Comparing to lion traits.",
      "example": "You're like a lion 游부",
      "riskLevel": "LOW"
    },
    {
      "context": "DATING",
      "meaning": "Cute animal reference.",
      "example": "My little lion 游부",
      "riskLevel": "LOW"
    },
    {
      "context": "IRONIC",
      "meaning": "Joking about animal behavior.",
      "example": "Acting wild 游부",
      "riskLevel": "LOW"
    }
  ],
  "platformNotes": [
    {
      "platform": "TWITTER",
      "note": "Used in posts about lion."
    },
    {
      "platform": "INSTAGRAM",
      "note": "Popular in captions and stories."
    },
    {
      "platform": "TIKTOK",
      "note": "Common in comments and reactions."
    }
  ],
  "generationalNotes": [
    {
      "generation": "GEN_Z",
      "note": "Uses 游부 in casual contexts."
    },
    {
      "generation": "MILLENNIAL",
      "note": "Familiar with 游부 across platforms."
    },
    {
      "generation": "BOOMER",
      "note": "May use 游부 literally."
    }
  ],
  "warnings": [],
  "relatedCombos": [],
  "seoTitle": "游부 Lion Emoji Meaning - What Does 游부 Really Mean?",
  "seoDescription": "Learn what the lion emoji 游부 really means in texts and social media."
}
