{
  "unicode": "U+1F91F-1F3FE",
  "slug": "love-you-gesture-medium-dark-skin-tone-emoji",
  "character": "🤟",
  "name": "Love You Gesture: Medium-Dark Skin Tone",
  "shortName": "love-you-gesture medium-dark",
  "category": "People & Body",
  "subcategory": "Hand Gesture",
  "unicodeVersion": "8.0",
  "baseMeaning": "Love You Gesture with medium-dark skin tone",
  "tldr": "Love You Gesture emoji with skin tone",
  "contextMeanings": [
    {
      "context": "LITERAL",
      "meaning": "Love You Gesture with skin tone modifier",
      "example": "🤟",
      "riskLevel": "LOW"
    },
    {
      "context": "SLANG",
      "meaning": "Personalized emoji representation",
      "example": "🤟",
      "riskLevel": "LOW"
    }
  ],
  "platformNotes": [
    {
      "platform": "TWITTER",
      "note": "Renders with skin tone modifier"
    },
    {
      "platform": "INSTAGRAM",
      "note": "Full skin tone support"
    }
  ],
  "generationalNotes": [
    {
      "generation": "GEN_Z",
      "note": "Commonly used for personalization"
    },
    {
      "generation": "MILLENNIAL",
      "note": "Standard skin tone usage"
    }
  ],
  "warnings": [],
  "relatedCombos": [],
  "seoTitle": "🤟 Love You Gesture Medium-Dark Skin Tone Emoji - Meaning",
  "seoDescription": "Learn what the Love You Gesture emoji with medium-dark skin tone means."
}
