{
  "unicode": "1F4E3",
  "slug": "megaphone",
  "character": "📣",
  "name": "Megaphone",
  "shortName": "megaphone",
  "category": "objects",
  "subcategory": "sound",
  "unicodeVersion": "6.0",
  "baseMeaning": "A megaphone or cheerleading cone for amplifying sound.",
  "tldr": "Announcement! Used for making announcements, cheering, or getting attention.",
  "contextMeanings": [
    {
      "context": "LITERAL",
      "meaning": "Making an announcement or cheering.",
      "example": "Big news 📣",
      "riskLevel": "LOW"
    },
    {
      "context": "SLANG",
      "meaning": "Drawing attention to something important.",
      "example": "Listen up 📣",
      "riskLevel": "LOW"
    },
    {
      "context": "WORK",
      "meaning": "Company announcements or updates.",
      "example": "Team update 📣",
      "riskLevel": "LOW"
    },
    {
      "context": "IRONIC",
      "meaning": "Loudly announcing something obvious.",
      "example": "BREAKING: water is wet 📣",
      "riskLevel": "LOW"
    }
  ],
  "platformNotes": [
    {
      "platform": "SLACK",
      "note": "Common for announcements and updates."
    },
    {
      "platform": "TWITTER",
      "note": "Used for important announcements."
    },
    {
      "platform": "INSTAGRAM",
      "note": "Popular for launch announcements."
    }
  ],
  "generationalNotes": [
    {
      "generation": "GEN_Z",
      "note": "Attention-grabbing and announcements."
    },
    {
      "generation": "MILLENNIAL",
      "note": "Cheerleading and announcements."
    },
    {
      "generation": "BOOMER",
      "note": "Megaphone for announcements."
    }
  ],
  "warnings": [],
  "relatedCombos": [],
  "seoTitle": "📣 Megaphone Emoji Meaning - What Does 📣 Really Mean?",
  "seoDescription": "Learn what the megaphone emoji 📣 really means. Used for announcements and getting attention. Complete context guide."
}
