{
  "unicode": "U+2716",
  "slug": "multiplication-x-emoji",
  "character": "✖",
  "name": "Multiplication X",
  "shortName": "multiplication x emoji",
  "category": "Symbols",
  "subcategory": "Math",
  "unicodeVersion": "13.0",
  "baseMeaning": "Multiplication sign",
  "tldr": "Times symbol",
  "contextMeanings": [
    {
      "context": "LITERAL",
      "meaning": "Multiplication",
      "example": "3 ✖ 3 = 9",
      "riskLevel": "LOW"
    },
    {
      "context": "SLANG",
      "meaning": "No or wrong",
      "example": "That's a ✖ from me",
      "riskLevel": "LOW"
    }
  ],
  "platformNotes": [
    {
      "platform": "TWITTER",
      "note": "Renders consistently across the platform"
    },
    {
      "platform": "INSTAGRAM",
      "note": "Common in stories and posts"
    }
  ],
  "generationalNotes": [
    {
      "generation": "GEN_Z",
      "note": "Used in various creative contexts"
    },
    {
      "generation": "MILLENNIAL",
      "note": "Straightforward usage"
    }
  ],
  "warnings": [],
  "relatedCombos": [],
  "seoTitle": "✖ Multiplication X Emoji Meaning - What Does ✖ Really Mean?",
  "seoDescription": "Learn what the multiplication x emoji ✖ really means in texts and social media."
}
