{
  "unicode": "1F51E",
  "slug": "no-one-under-eighteen-emoji",
  "character": "🔞",
  "name": "No One Under Eighteen",
  "shortName": "no one under eighteen emoji",
  "category": "symbols",
  "subcategory": "warning",
  "unicodeVersion": "13.0",
  "baseMeaning": "Age restriction.",
  "tldr": "Represents adult content.",
  "contextMeanings": [
    {
      "context": "LITERAL",
      "meaning": "18+ content.",
      "example": "Adults only 🔞",
      "riskLevel": "LOW"
    },
    {
      "context": "SLANG",
      "meaning": "NSFW.",
      "example": "Not for kids 🔞",
      "riskLevel": "LOW"
    }
  ],
  "platformNotes": [
    {
      "platform": "TWITTER",
      "note": "Used in posts about no one under eighteen."
    },
    {
      "platform": "INSTAGRAM",
      "note": "Popular in captions and stories."
    },
    {
      "platform": "TIKTOK",
      "note": "Common in comments and reactions."
    }
  ],
  "generationalNotes": [
    {
      "generation": "GEN_Z",
      "note": "Uses 🔞 in casual contexts."
    },
    {
      "generation": "MILLENNIAL",
      "note": "Familiar with 🔞 across platforms."
    },
    {
      "generation": "BOOMER",
      "note": "May use 🔞 literally."
    }
  ],
  "warnings": [],
  "relatedCombos": [],
  "seoTitle": "🔞 No One Under Eighteen Emoji Meaning - What Does 🔞 Really Mean?",
  "seoDescription": "Learn what the no one under eighteen emoji 🔞 really means in texts and social media."
}
