{
  "unicode": "1F48D",
  "slug": "ring",
  "character": "💍",
  "name": "Ring",
  "shortName": "ring",
  "category": "objects",
  "subcategory": "clothing",
  "unicodeVersion": "6.0",
  "baseMeaning": "Ring emoji.",
  "tldr": "Ring!",
  "contextMeanings": [
    {
      "context": "LITERAL",
      "meaning": "Represents Ring.",
      "example": "Look at this 💍",
      "riskLevel": "LOW"
    },
    {
      "context": "SLANG",
      "meaning": "Engaged or marriage.",
      "example": "Feeling 💍",
      "riskLevel": "LOW"
    },
    { "context": "IRONIC", "meaning": "Ironic usage.", "example": "Mood 💍", "riskLevel": "LOW" },
    {
      "context": "WORK",
      "meaning": "Work context.",
      "example": "Work vibes 💍",
      "riskLevel": "LOW"
    }
  ],
  "platformNotes": [
    { "platform": "TWITTER", "note": "Common usage." },
    { "platform": "INSTAGRAM", "note": "Popular posts." },
    { "platform": "TIKTOK", "note": "Trending." }
  ],
  "generationalNotes": [
    { "generation": "GEN_Z", "note": "Gen Z usage." },
    { "generation": "MILLENNIAL", "note": "Millennial usage." },
    { "generation": "BOOMER", "note": "Boomer interpretation." }
  ],
  "warnings": [],
  "relatedCombos": [],
  "seoTitle": "💍 Ring Emoji Meaning",
  "seoDescription": "Learn what the Ring emoji 💍 really means."
}
