{
  "unicode": "1F914",
  "slug": "thinking-face-emoji",
  "character": "🤔",
  "name": "Thinking Face",
  "shortName": "thinking face emoji",
  "category": "people",
  "subcategory": "face-hand",
  "unicodeVersion": "13.0",
  "baseMeaning": "Thinking emoji.",
  "tldr": "Represents pondering.",
  "contextMeanings": [
    {
      "context": "LITERAL",
      "meaning": "Deep in thought.",
      "example": "Let me think 🤔",
      "riskLevel": "LOW"
    },
    {
      "context": "SLANG",
      "meaning": "Suspicious or doubtful.",
      "example": "Hmm 🤔",
      "riskLevel": "LOW"
    }
  ],
  "platformNotes": [
    {
      "platform": "TWITTER",
      "note": "Used in posts about thinking face."
    },
    {
      "platform": "INSTAGRAM",
      "note": "Popular in captions and stories."
    },
    {
      "platform": "TIKTOK",
      "note": "Common in comments and reactions."
    }
  ],
  "generationalNotes": [
    {
      "generation": "GEN_Z",
      "note": "Uses 🤔 in casual contexts."
    },
    {
      "generation": "MILLENNIAL",
      "note": "Familiar with 🤔 across platforms."
    },
    {
      "generation": "BOOMER",
      "note": "May use 🤔 literally."
    }
  ],
  "warnings": [],
  "relatedCombos": [],
  "seoTitle": "🤔 Thinking Face Emoji Meaning - What Does 🤔 Really Mean?",
  "seoDescription": "Learn what the thinking face emoji 🤔 really means in texts and social media."
}
