{
  "unicode": "1F44E",
  "slug": "thumbs-down-emoji",
  "character": "👎",
  "name": "Thumbs Down",
  "shortName": "thumbs down emoji",
  "category": "people",
  "subcategory": "hand-fingers-closed",
  "unicodeVersion": "13.0",
  "baseMeaning": "Thumbs down.",
  "tldr": "Represents disapproval.",
  "contextMeanings": [
    {
      "context": "LITERAL",
      "meaning": "Thumbs down gesture.",
      "example": "Not good 👎",
      "riskLevel": "LOW"
    },
    {
      "context": "SLANG",
      "meaning": "Dislike or no.",
      "example": "Hard pass 👎",
      "riskLevel": "LOW"
    }
  ],
  "platformNotes": [
    {
      "platform": "TWITTER",
      "note": "Used in posts about thumbs down."
    },
    {
      "platform": "INSTAGRAM",
      "note": "Popular in captions and stories."
    },
    {
      "platform": "TIKTOK",
      "note": "Common in comments and reactions."
    }
  ],
  "generationalNotes": [
    {
      "generation": "GEN_Z",
      "note": "Uses 👎 in casual contexts."
    },
    {
      "generation": "MILLENNIAL",
      "note": "Familiar with 👎 across platforms."
    },
    {
      "generation": "BOOMER",
      "note": "May use 👎 literally."
    }
  ],
  "warnings": [],
  "relatedCombos": [],
  "seoTitle": "👎 Thumbs Down Emoji Meaning - What Does 👎 Really Mean?",
  "seoDescription": "Learn what the thumbs down emoji 👎 really means in texts and social media."
}
