{
  "unicode": "1F405",
  "slug": "tiger",
  "character": "游낸",
  "name": "Tiger",
  "shortName": "tiger",
  "category": "animals",
  "subcategory": "animal-mammal",
  "unicodeVersion": "6.0",
  "baseMeaning": "A tiger.",
  "tldr": "Tiger! Fierce or powerful.",
  "contextMeanings": [
    {
      "context": "LITERAL",
      "meaning": "Represents a tiger.",
      "example": "Tiger stripes 游낸",
      "riskLevel": "LOW"
    },
    {
      "context": "SLANG",
      "meaning": "Fierce, powerful, or Year of Tiger.",
      "example": "Tiger mode 游낸",
      "riskLevel": "LOW"
    },
    { "context": "IRONIC", "meaning": "Acting fierce.", "example": "Rawr 游낸", "riskLevel": "LOW" },
    {
      "context": "WORK",
      "meaning": "Aggressive approach.",
      "example": "Go get it tiger 游낸",
      "riskLevel": "LOW"
    }
  ],
  "platformNotes": [
    { "platform": "TWITTER", "note": "Fierce and powerful." },
    { "platform": "INSTAGRAM", "note": "Animal aesthetic." },
    { "platform": "TIKTOK", "note": "Tiger content." }
  ],
  "generationalNotes": [
    { "generation": "GEN_Z", "note": "Fierce energy." },
    { "generation": "MILLENNIAL", "note": "Tiger King era." },
    { "generation": "BOOMER", "note": "Wild animal." }
  ],
  "warnings": [],
  "relatedCombos": [],
  "seoTitle": "游낸 Tiger Emoji Meaning",
  "seoDescription": "Learn what the Tiger emoji 游낸 really means."
}
