{
  "unicode": "1F6BD",
  "slug": "toilet-emoji",
  "character": "🚽",
  "name": "Toilet",
  "shortName": "toilet emoji",
  "category": "objects",
  "subcategory": "household",
  "unicodeVersion": "13.0",
  "baseMeaning": "Toilet emoji.",
  "tldr": "Represents toilet.",
  "contextMeanings": [
    {
      "context": "LITERAL",
      "meaning": "The toilet object.",
      "example": "Using toilet 🚽",
      "riskLevel": "LOW"
    },
    {
      "context": "SLANG",
      "meaning": "Reference to the object's use.",
      "example": "Need this 🚽",
      "riskLevel": "LOW"
    },
    {
      "context": "WORK",
      "meaning": "Professional context.",
      "example": "For work 🚽",
      "riskLevel": "LOW"
    },
    {
      "context": "IRONIC",
      "meaning": "Sarcastic reference.",
      "example": "Very fancy 🚽",
      "riskLevel": "LOW"
    }
  ],
  "platformNotes": [
    {
      "platform": "TWITTER",
      "note": "Used in posts about toilet."
    },
    {
      "platform": "INSTAGRAM",
      "note": "Popular in captions and stories."
    },
    {
      "platform": "TIKTOK",
      "note": "Common in comments and reactions."
    }
  ],
  "generationalNotes": [
    {
      "generation": "GEN_Z",
      "note": "Uses 🚽 in casual contexts."
    },
    {
      "generation": "MILLENNIAL",
      "note": "Familiar with 🚽 across platforms."
    },
    {
      "generation": "BOOMER",
      "note": "May use 🚽 literally."
    }
  ],
  "warnings": [],
  "relatedCombos": [],
  "seoTitle": "🚽 Toilet Emoji Meaning - What Does 🚽 Really Mean?",
  "seoDescription": "Learn what the toilet emoji 🚽 really means in texts and social media."
}
