{
  "unicode": "3030",
  "slug": "wavy-dash-emoji",
  "character": "〰",
  "name": "Wavy Dash",
  "shortName": "wavy dash emoji",
  "category": "symbols",
  "subcategory": "other-symbol",
  "unicodeVersion": "13.0",
  "baseMeaning": "A wavy line.",
  "tldr": "Represents continuation.",
  "contextMeanings": [
    {
      "context": "LITERAL",
      "meaning": "A wavy dash.",
      "example": "And so on 〰",
      "riskLevel": "LOW"
    },
    {
      "context": "SLANG",
      "meaning": "Etc.",
      "example": "More stuff 〰",
      "riskLevel": "LOW"
    }
  ],
  "platformNotes": [
    {
      "platform": "TWITTER",
      "note": "Used in posts about wavy dash."
    },
    {
      "platform": "INSTAGRAM",
      "note": "Popular in captions and stories."
    },
    {
      "platform": "TIKTOK",
      "note": "Common in comments and reactions."
    }
  ],
  "generationalNotes": [
    {
      "generation": "GEN_Z",
      "note": "Uses 〰 in casual contexts."
    },
    {
      "generation": "MILLENNIAL",
      "note": "Familiar with 〰 across platforms."
    },
    {
      "generation": "BOOMER",
      "note": "May use 〰 literally."
    }
  ],
  "warnings": [],
  "relatedCombos": [],
  "seoTitle": "〰 Wavy Dash Emoji Meaning - What Does 〰 Really Mean?",
  "seoDescription": "Learn what the wavy dash emoji 〰 really means in texts and social media."
}
