{
  "unicode": "262F",
  "slug": "yin-yang-emoji",
  "character": "☯",
  "name": "Yin Yang",
  "shortName": "yin yang emoji",
  "category": "symbols",
  "subcategory": "religion",
  "unicodeVersion": "13.0",
  "baseMeaning": "Yin yang symbol.",
  "tldr": "Represents balance.",
  "contextMeanings": [
    {
      "context": "LITERAL",
      "meaning": "Taoist yin yang symbol.",
      "example": "Finding balance ☯",
      "riskLevel": "LOW"
    },
    {
      "context": "SLANG",
      "meaning": "Balance or harmony.",
      "example": "Life is about balance ☯",
      "riskLevel": "LOW"
    }
  ],
  "platformNotes": [
    {
      "platform": "TWITTER",
      "note": "Used in posts about yin yang."
    },
    {
      "platform": "INSTAGRAM",
      "note": "Popular in captions and stories."
    },
    {
      "platform": "TIKTOK",
      "note": "Common in comments and reactions."
    }
  ],
  "generationalNotes": [
    {
      "generation": "GEN_Z",
      "note": "Uses ☯ in casual contexts."
    },
    {
      "generation": "MILLENNIAL",
      "note": "Familiar with ☯ across platforms."
    },
    {
      "generation": "BOOMER",
      "note": "May use ☯ literally."
    }
  ],
  "warnings": [],
  "relatedCombos": [],
  "seoTitle": "☯ Yin Yang Emoji Meaning - What Does ☯ Really Mean?",
  "seoDescription": "Learn what the yin yang emoji ☯ really means in texts and social media."
}
